spreadsheetconverter/__init__.py
spreadsheetconverter/config.py
spreadsheetconverter/converter.py
spreadsheetconverter/exceptions.py
spreadsheetconverter/utils.py
spreadsheetconverter/handler/__init__.py
spreadsheetconverter/handler/base.py
spreadsheetconverter/handler/json.py
spreadsheetconverter/handler/inspector/__init__.py
spreadsheetconverter/handler/inspector/base.py
spreadsheetconverter/handler/inspector/number_gt.py
spreadsheetconverter/handler/inspector/number_gte.py
spreadsheetconverter/handler/inspector/number_lt.py
spreadsheetconverter/handler/inspector/number_lte.py
spreadsheetconverter/handler/inspector/number_range.py
spreadsheetconverter/handler/valueformatter/__init__.py
spreadsheetconverter/handler/valueformatter/base.py
spreadsheetconverter/handler/valueformatter/string.py
spreadsheetconverter/loader/__init__.py
spreadsheetconverter/loader/base.py
spreadsheetconverter/loader/xls.py
spreadsheetconverter/loader/validator/__init__.py
spreadsheetconverter/loader/validator/base.py
spreadsheetconverter/loader/validator/unique.py
spreadsheetconverter/loader/valueconverter/__init__.py
spreadsheetconverter/loader/valueconverter/base.py
spreadsheetconverter/loader/valueconverter/bool.py
spreadsheetconverter/loader/valueconverter/char.py
spreadsheetconverter/loader/valueconverter/date.py
spreadsheetconverter/loader/valueconverter/datetime.py
spreadsheetconverter/loader/valueconverter/float.py
spreadsheetconverter/loader/valueconverter/foreignkey.py
spreadsheetconverter/loader/valueconverter/int.py
spreadsheetconverter/scripts/__init__.py
spreadsheetconverter/scripts/convert.py
tests/__init__.py
tests/conftest.py
tests/test_convert.py
SpreadsheetConverter-0.2.0.dist-info/LICENSE.txt
SpreadsheetConverter-0.2.0.dist-info/METADATA
SpreadsheetConverter-0.2.0.dist-info/WHEEL
SpreadsheetConverter-0.2.0.dist-info/entry_points.txt
SpreadsheetConverter-0.2.0.dist-info/top_level.txt
SpreadsheetConverter-0.2.0.dist-info/RECORD
