Metadata-Version: 2.1
Name: SpreadsheetConverter
Version: 0.2.0
Summary: Spreadsheet Converter
Home-page: https://github.com/gumi/spreadsheetconverter/
Author: Yugo Shimizu
Author-email: yugo.shimizu@gu3.co.jp
Maintainer: Yugo Shimizu
Maintainer-email: yugo.shimizu@gu3.co.jp
License: MIT
Platform: UNKNOWN
Classifier: Programming Language :: Python :: 3
Classifier: Programming Language :: Python :: 3.6
Classifier: Programming Language :: Python :: 3.7
Classifier: Programming Language :: Python :: 3.8
Classifier: Programming Language :: Python :: Implementation :: CPython
Classifier: License :: OSI Approved :: MIT License
License-File: LICENSE.txt
Requires-Dist: PyYAML (==6.0)
Requires-Dist: python-dateutil (==2.8.2)
Requires-Dist: pytz (==2022.1)
Requires-Dist: six (==1.16.0)
Requires-Dist: xlrd (==2.0.1)
Provides-Extra: testing
Requires-Dist: pytest ; extra == 'testing'
